<?xml version="1.0" encoding="utf-8" ?> 

<NEKTAR> 

<GEOMETRY DIM="1" SPACE="2"> 

	 <VERTEX> 
		 <V ID="0"> 0.000    0.0    0.0 </V> 
		 <V ID="1"> 5.718    0.0    0.0 </V> 

		 <V ID="2"> 5.718    -16.0    0.0 </V> 
		 <V ID="3"> 7.986    -16.0    0.0 </V> 

		 <V ID="4"> 5.718    5.0    0.0 </V> 
		 <V ID="5"> 9.563    5.0    0.0 </V> 

		 <V ID="6"> 9.563    3.0    0.0 </V> 
		 <V ID="7"> 13.408    3.0    0.0 </V> 

		 <V ID="8"> 9.563    8.4    0.0 </V> 
		 <V ID="9"> 20.211    8.4    0.0 </V> 

		 <V ID="10"> 13.408    1.5    0.0 </V> 
		 <V ID="11"> 30.267    1.5    0.0 </V> 

		 <V ID="12"> 13.408    4.5    0.0 </V> 
		 <V ID="13"> 61.224    4.5    0.0 </V> 

		 <V ID="14"> 61.224    3.5    0.0 </V> 
		 <V ID="15"> 87.844    3.5    0.0 </V> 

		 <V ID="16"> 61.224    6.0    0.0 </V> 
		 <V ID="17"> 68.816    6.0    0.0 </V> 

		 <V ID="18"> 68.816    5.0    0.0 </V> 
		 <V ID="19"> 77.787    5.0    0.0 </V> 

		 <V ID="20"> 68.816    8.0    0.0 </V> 
		 <V ID="21"> 88.238    8.0    0.0 </V> 

		 <V ID="22"> 20.211    6.5    0.0 </V> 
		 <V ID="23"> 40.422    6.5    0.0 </V> 

		 <V ID="24"> 20.211    12.0    0.0 </V> 
		 <V ID="25"> 38.647    12.0    0.0 </V> 

		 <V ID="26"> 7.986    -30.0    0.0 </V> 
		 <V ID="27"> 12.422    -30.0    0.0 </V> 

		 <V ID="28"> 7.986    -7.0    0.0 </V> 
		 <V ID="29"> 23.760    -7.0    0.0 </V> 

		 <V ID="30"> 23.760    -9.0    0.0 </V> 
		 <V ID="31"> 43.971    -9.0    0.0 </V> 

		 <V ID="32"> 23.760    -4.0    0.0 </V> 
		 <V ID="33"> 42.196    -4.0    0.0 </V> 

		 <V ID="34"> 12.422    -36.0    0.0 </V> 
		 <V ID="35"> 18.338    -36.0    0.0 </V> 

		 <V ID="36"> 12.422    -25.0    0.0 </V> 
		 <V ID="37"> 16.267    -25.0    0.0 </V> 

		 <V ID="38"> 16.267    -28.0    0.0 </V> 
		 <V ID="39"> 33.028    -28.0    0.0 </V> 

		 <V ID="40"> 16.267    -22.5    0.0 </V> 
		 <V ID="41"> 64.083    -22.5    0.0 </V> 

		 <V ID="42"> 64.083    -25.0    0.0 </V> 
		 <V ID="43"> 90.703    -25.0    0.0 </V> 

		 <V ID="44"> 64.083    -20.0    0.0 </V> 
		 <V ID="45"> 71.675    -20.0    0.0 </V> 

		 <V ID="46"> 71.675    -22.0    0.0 </V> 
		 <V ID="47"> 80.647    -22.0    0.0 </V> 

		 <V ID="48"> 71.675    -15.5    0.0 </V> 
		 <V ID="49"> 91.097    -15.5    0.0 </V> 

		 <V ID="50"> 18.338    -32.0    0.0 </V> 
		 <V ID="51"> 27.408    -32.0    0.0 </V> 

		 <V ID="52"> 18.338    -42.0    0.0 </V> 
		 <V ID="53"> 30.169    -42.0    0.0 </V> 

		 <V ID="54"> 30.169    -30.0    0.0 </V> 
		 <V ID="55"> 36.183    -30.0    0.0 </V> 

		 <V ID="56"> 30.169    -48.0    0.0 </V> 
		 <V ID="57"> 32.436    -48.0    0.0 </V> 

		 <V ID="58"> 32.436    -55.0    0.0 </V> 
		 <V ID="59"> 34.704    -55.0    0.0 </V> 

		 <V ID="60"> 32.436    -45.0    0.0 </V> 
		 <V ID="61"> 39.929    -45.0    0.0 </V> 

		 <V ID="62"> 34.704    -60.0    0.0 </V> 
		 <V ID="63"> 42.788    -60.0    0.0 </V> 

		 <V ID="64"> 34.704    -50.0    0.0 </V> 
		 <V ID="65"> 41.802    -50.0    0.0 </V> 

		 <V ID="66"> 36.183    -28.0    0.0 </V> 
		 <V ID="67"> 42.887    -28.0    0.0 </V> 

		 <V ID="68"> 36.183    -32.0    0.0 </V> 
		 <V ID="69"> 38.450    -32.0    0.0 </V> 

		 <V ID="70"> 38.450    -30.0    0.0 </V> 
		 <V ID="71"> 42.098    -30.0    0.0 </V> 

		 <V ID="72"> 38.450    -35.0    0.0 </V> 
		 <V ID="73"> 40.718    -35.0    0.0 </V> 

		 <V ID="74"> 40.718    -33.0    0.0 </V> 
		 <V ID="75"> 44.365    -33.0    0.0 </V> 

		 <V ID="76"> 40.718    -36.0    0.0 </V> 
		 <V ID="77"> 52.746    -36.0    0.0 </V> 

		 <V ID="78"> 52.746    -38.0    0.0 </V> 
		 <V ID="79"> 58.464    -38.0    0.0 </V> 

		 <V ID="80"> 52.746    -34.0    0.0 </V> 
		 <V ID="81"> 55.013    -34.0    0.0 </V> 

		 <V ID="82"> 55.013    -32.0    0.0 </V> 
		 <V ID="83"> 61.717    -32.0    0.0 </V> 

		 <V ID="84"> 55.013    -35.0    0.0 </V> 
		 <V ID="85"> 61.717    -35.0    0.0 </V> 

		 <V ID="86"> 61.717    -30.0    0.0 </V> 
		 <V ID="87"> 78.083    -30.0    0.0 </V> 

		 <V ID="88"> 61.717    -34.0    0.0 </V> 
		 <V ID="89"> 67.436    -34.0    0.0 </V> 

		 <V ID="90"> 78.083    -29.0    0.0 </V> 
		 <V ID="91"> 128.265    -29.0    0.0 </V> 

		 <V ID="92"> 78.083    -33.0    0.0 </V> 
		 <V ID="93"> 92.379    -33.0    0.0 </V> 

		 <V ID="94"> 128.265    -30.0    0.0 </V> 
		 <V ID="95"> 164.645    -30.0    0.0 </V> 

		 <V ID="96"> 128.265    -28.0    0.0 </V> 
		 <V ID="97"> 167.504    -28.0    0.0 </V> 

		 <V ID="98"> 61.717    -35.5    0.0 </V> 
		 <V ID="99"> 78.083    -35.5    0.0 </V> 

		 <V ID="100"> 61.717    -37.0    0.0 </V> 
		 <V ID="101"> 67.436    -37.0    0.0 </V> 

		 <V ID="102"> 78.083    -39.0    0.0 </V> 
		 <V ID="103"> 128.265    -39.0    0.0 </V> 

		 <V ID="104"> 78.083    -34.0    0.0 </V> 
		 <V ID="105"> 92.379    -34.0    0.0 </V> 

		 <V ID="106"> 128.265    -37.5    0.0 </V> 
		 <V ID="107"> 164.645    -37.5    0.0 </V> 

		 <V ID="108"> 128.265    -45.0    0.0 </V> 
		 <V ID="109"> 167.504    -45.0    0.0 </V> 
	 </VERTEX> 

	 <ELEMENT> 
		 <S ID="0"> 0 1 </S> 
		 <S ID="1"> 1 2 </S> 
		 <S ID="2"> 1 4 </S> 
		 <S ID="3"> 2 3 </S> 
		 <S ID="4"> 4 5 </S> 
		 <S ID="5"> 5 6 </S> 
		 <S ID="6"> 5 8 </S> 
		 <S ID="7"> 6 7 </S> 
		 <S ID="8"> 8 9 </S> 
		 <S ID="9"> 7 10 </S> 
		 <S ID="10"> 7 12 </S> 
		 <S ID="11"> 10 11 </S> 
		 <S ID="12"> 12 13 </S> 
		 <S ID="13"> 13 14 </S> 
		 <S ID="14"> 13 16 </S> 
		 <S ID="15"> 14 15 </S> 
		 <S ID="16"> 16 17 </S> 
		 <S ID="17"> 17 18 </S> 
		 <S ID="18"> 17 20 </S> 
		 <S ID="19"> 18 19 </S> 
		 <S ID="20"> 20 21 </S> 
		 <S ID="21"> 9 22 </S> 
		 <S ID="22"> 9 24 </S> 
		 <S ID="23"> 22 23 </S> 
		 <S ID="24"> 24 25 </S> 
		 <S ID="25"> 3 26 </S> 
		 <S ID="26"> 3 28 </S> 
		 <S ID="27"> 26 27 </S> 
		 <S ID="28"> 28 29 </S> 
		 <S ID="29"> 29 30 </S> 
		 <S ID="30"> 29 32 </S> 
		 <S ID="31"> 30 31 </S> 
		 <S ID="32"> 32 33 </S> 
		 <S ID="33"> 27 34 </S> 
		 <S ID="34"> 27 36 </S> 
		 <S ID="35"> 34 35 </S> 
		 <S ID="36"> 36 37 </S> 
		 <S ID="37"> 37 38 </S> 
		 <S ID="38"> 37 40 </S> 
		 <S ID="39"> 38 39 </S> 
		 <S ID="40"> 40 41 </S> 
		 <S ID="41"> 41 42 </S> 
		 <S ID="42"> 41 44 </S> 
		 <S ID="43"> 42 43 </S> 
		 <S ID="44"> 44 45 </S> 
		 <S ID="45"> 45 46 </S> 
		 <S ID="46"> 45 48 </S> 
		 <S ID="47"> 46 47 </S> 
		 <S ID="48"> 48 49 </S> 
		 <S ID="49"> 35 50 </S> 
		 <S ID="50"> 35 52 </S> 
		 <S ID="51"> 50 51 </S> 
		 <S ID="52"> 52 53 </S> 
		 <S ID="53"> 53 54 </S> 
		 <S ID="54"> 53 56 </S> 
		 <S ID="55"> 54 55 </S> 
		 <S ID="56"> 56 57 </S> 
		 <S ID="57"> 57 58 </S> 
		 <S ID="58"> 57 60 </S> 
		 <S ID="59"> 58 59 </S> 
		 <S ID="60"> 60 61 </S> 
		 <S ID="61"> 59 62 </S> 
		 <S ID="62"> 59 64 </S> 
		 <S ID="63"> 62 63 </S> 
		 <S ID="64"> 64 65 </S> 
		 <S ID="65"> 55 66 </S> 
		 <S ID="66"> 55 68 </S> 
		 <S ID="67"> 66 67 </S> 
		 <S ID="68"> 68 69 </S> 
		 <S ID="69"> 69 70 </S> 
		 <S ID="70"> 69 72 </S> 
		 <S ID="71"> 70 71 </S> 
		 <S ID="72"> 72 73 </S> 
		 <S ID="73"> 73 74 </S> 
		 <S ID="74"> 73 76 </S> 
		 <S ID="75"> 74 75 </S> 
		 <S ID="76"> 76 77 </S> 
		 <S ID="77"> 77 78 </S> 
		 <S ID="78"> 77 80 </S> 
		 <S ID="79"> 78 79 </S> 
		 <S ID="80"> 80 81 </S> 
		 <S ID="81"> 81 82 </S> 
		 <S ID="82"> 81 84 </S> 
		 <S ID="83"> 82 83 </S> 
		 <S ID="84"> 84 85 </S> 
		 <S ID="85"> 83 86 </S> 
		 <S ID="86"> 83 88 </S> 
		 <S ID="87"> 86 87 </S> 
		 <S ID="88"> 88 89 </S> 
		 <S ID="89"> 87 90 </S> 
		 <S ID="90"> 87 92 </S> 
		 <S ID="91"> 90 91 </S> 
		 <S ID="92"> 92 93 </S> 
		 <S ID="93"> 91 94 </S> 
		 <S ID="94"> 91 96 </S> 
		 <S ID="95"> 94 95 </S> 
		 <S ID="96"> 96 97 </S> 
		 <S ID="97"> 85 98 </S> 
		 <S ID="98"> 85 100 </S> 
		 <S ID="99"> 98 99 </S> 
		 <S ID="100"> 100 101 </S> 
		 <S ID="101"> 99 102 </S> 
		 <S ID="102"> 99 104 </S> 
		 <S ID="103"> 102 103 </S> 
		 <S ID="104"> 104 105 </S> 
		 <S ID="105"> 103 106 </S> 
		 <S ID="106"> 103 108 </S> 
		 <S ID="107"> 106 107 </S> 
		 <S ID="108"> 108 109 </S> 
	 </ELEMENT> 

	 <COMPOSITE> 
		 <C ID="0"> S[0] </C> 
		 <C ID="1"> V[0] </C> 
		 <C ID="2"> V[1] </C> 

		 <C ID="3"> S[1,3] </C> 
		 <C ID="4"> V[2] </C> 
		 <C ID="5"> V[3] </C> 

		 <C ID="6"> S[2,4] </C> 
		 <C ID="7"> V[4] </C> 
		 <C ID="8"> V[5] </C> 

		 <C ID="9"> S[5,7] </C> 
		 <C ID="10"> V[6] </C> 
		 <C ID="11"> V[7] </C> 

		 <C ID="12"> S[6,8] </C> 
		 <C ID="13"> V[8] </C> 
		 <C ID="14"> V[9] </C> 

		 <C ID="15"> S[9,11] </C> 
		 <C ID="16"> V[10] </C> 
		 <C ID="17"> V[11] </C> 

		 <C ID="18"> S[10,12] </C> 
		 <C ID="19"> V[12] </C> 
		 <C ID="20"> V[13] </C> 

		 <C ID="21"> S[13,15] </C> 
		 <C ID="22"> V[14] </C> 
		 <C ID="23"> V[15] </C> 

		 <C ID="24"> S[14,16] </C> 
		 <C ID="25"> V[16] </C> 
		 <C ID="26"> V[17] </C> 

		 <C ID="27"> S[17,19] </C> 
		 <C ID="28"> V[18] </C> 
		 <C ID="29"> V[19] </C> 

		 <C ID="30"> S[18,20] </C> 
		 <C ID="31"> V[20] </C> 
		 <C ID="32"> V[21] </C> 

		 <C ID="33"> S[21,23] </C> 
		 <C ID="34"> V[22] </C> 
		 <C ID="35"> V[23] </C> 

		 <C ID="36"> S[22,24] </C> 
		 <C ID="37"> V[24] </C> 
		 <C ID="38"> V[25] </C> 

		 <C ID="39"> S[25,27] </C> 
		 <C ID="40"> V[26] </C> 
		 <C ID="41"> V[27] </C> 

		 <C ID="42"> S[26,28] </C> 
		 <C ID="43"> V[28] </C> 
		 <C ID="44"> V[29] </C> 

		 <C ID="45"> S[29,31] </C> 
		 <C ID="46"> V[30] </C> 
		 <C ID="47"> V[31] </C> 

		 <C ID="48"> S[30,32] </C> 
		 <C ID="49"> V[32] </C> 
		 <C ID="50"> V[33] </C> 

		 <C ID="51"> S[33,35] </C> 
		 <C ID="52"> V[34] </C> 
		 <C ID="53"> V[35] </C> 

		 <C ID="54"> S[34,36] </C> 
		 <C ID="55"> V[36] </C> 
		 <C ID="56"> V[37] </C> 

		 <C ID="57"> S[37,39] </C> 
		 <C ID="58"> V[38] </C> 
		 <C ID="59"> V[39] </C> 

		 <C ID="60"> S[38,40] </C> 
		 <C ID="61"> V[40] </C> 
		 <C ID="62"> V[41] </C> 

		 <C ID="63"> S[41,43] </C> 
		 <C ID="64"> V[42] </C> 
		 <C ID="65"> V[43] </C> 

		 <C ID="66"> S[42,44] </C> 
		 <C ID="67"> V[44] </C> 
		 <C ID="68"> V[45] </C> 

		 <C ID="69"> S[45,47] </C> 
		 <C ID="70"> V[46] </C> 
		 <C ID="71"> V[47] </C> 

		 <C ID="72"> S[46,48] </C> 
		 <C ID="73"> V[48] </C> 
		 <C ID="74"> V[49] </C> 

		 <C ID="75"> S[49,51] </C> 
		 <C ID="76"> V[50] </C> 
		 <C ID="77"> V[51] </C> 

		 <C ID="78"> S[50,52] </C> 
		 <C ID="79"> V[52] </C> 
		 <C ID="80"> V[53] </C> 

		 <C ID="81"> S[53,55] </C> 
		 <C ID="82"> V[54] </C> 
		 <C ID="83"> V[55] </C> 

		 <C ID="84"> S[54,56] </C> 
		 <C ID="85"> V[56] </C> 
		 <C ID="86"> V[57] </C> 

		 <C ID="87"> S[57,59] </C> 
		 <C ID="88"> V[58] </C> 
		 <C ID="89"> V[59] </C> 

		 <C ID="90"> S[58,60] </C> 
		 <C ID="91"> V[60] </C> 
		 <C ID="92"> V[61] </C> 

		 <C ID="93"> S[61,63] </C> 
		 <C ID="94"> V[62] </C> 
		 <C ID="95"> V[63] </C> 

		 <C ID="96"> S[62,64] </C> 
		 <C ID="97"> V[64] </C> 
		 <C ID="98"> V[65] </C> 

		 <C ID="99"> S[65,67] </C> 
		 <C ID="100"> V[66] </C> 
		 <C ID="101"> V[67] </C> 

		 <C ID="102"> S[66,68] </C> 
		 <C ID="103"> V[68] </C> 
		 <C ID="104"> V[69] </C> 

		 <C ID="105"> S[69,71] </C> 
		 <C ID="106"> V[70] </C> 
		 <C ID="107"> V[71] </C> 

		 <C ID="108"> S[70,72] </C> 
		 <C ID="109"> V[72] </C> 
		 <C ID="110"> V[73] </C> 

		 <C ID="111"> S[73,75] </C> 
		 <C ID="112"> V[74] </C> 
		 <C ID="113"> V[75] </C> 

		 <C ID="114"> S[74,76] </C> 
		 <C ID="115"> V[76] </C> 
		 <C ID="116"> V[77] </C> 

		 <C ID="117"> S[77,79] </C> 
		 <C ID="118"> V[78] </C> 
		 <C ID="119"> V[79] </C> 

		 <C ID="120"> S[78,80] </C> 
		 <C ID="121"> V[80] </C> 
		 <C ID="122"> V[81] </C> 

		 <C ID="123"> S[81,83] </C> 
		 <C ID="124"> V[82] </C> 
		 <C ID="125"> V[83] </C> 

		 <C ID="126"> S[82,84] </C> 
		 <C ID="127"> V[84] </C> 
		 <C ID="128"> V[85] </C> 

		 <C ID="129"> S[85,87] </C> 
		 <C ID="130"> V[86] </C> 
		 <C ID="131"> V[87] </C> 

		 <C ID="132"> S[86,88] </C> 
		 <C ID="133"> V[88] </C> 
		 <C ID="134"> V[89] </C> 

		 <C ID="135"> S[89,91] </C> 
		 <C ID="136"> V[90] </C> 
		 <C ID="137"> V[91] </C> 

		 <C ID="138"> S[90,92] </C> 
		 <C ID="139"> V[92] </C> 
		 <C ID="140"> V[93] </C> 

		 <C ID="141"> S[93,95] </C> 
		 <C ID="142"> V[94] </C> 
		 <C ID="143"> V[95] </C> 

		 <C ID="144"> S[94,96] </C> 
		 <C ID="145"> V[96] </C> 
		 <C ID="146"> V[97] </C> 

		 <C ID="147"> S[97,99] </C> 
		 <C ID="148"> V[98] </C> 
		 <C ID="149"> V[99] </C> 

		 <C ID="150"> S[98,100] </C> 
		 <C ID="151"> V[100] </C> 
		 <C ID="152"> V[101] </C> 

		 <C ID="153"> S[101,103] </C> 
		 <C ID="154"> V[102] </C> 
		 <C ID="155"> V[103] </C> 

		 <C ID="156"> S[102,104] </C> 
		 <C ID="157"> V[104] </C> 
		 <C ID="158"> V[105] </C> 

		 <C ID="159"> S[105,107] </C> 
		 <C ID="160"> V[106] </C> 
		 <C ID="161"> V[107] </C> 

		 <C ID="162"> S[106,108] </C> 
		 <C ID="163"> V[108] </C> 
		 <C ID="164"> V[109] </C> 
	 </COMPOSITE> 

	 <DOMAIN> 
		 <D ID="0">    C[0] </D> 
		 <D ID="1">    C[3] </D> 
		 <D ID="2">    C[6] </D> 
		 <D ID="3">    C[9] </D> 
		 <D ID="4">   C[12] </D> 
		 <D ID="5">   C[15] </D> 
		 <D ID="6">   C[18] </D> 
		 <D ID="7">   C[21] </D> 
		 <D ID="8">   C[24] </D> 
		 <D ID="9">   C[27] </D> 
		 <D ID="10">  C[30] </D> 
		 <D ID="11">  C[33] </D> 
		 <D ID="12">  C[36] </D> 
		 <D ID="13">  C[39] </D> 
		 <D ID="14">  C[42] </D> 
		 <D ID="15">  C[45] </D> 
		 <D ID="16">  C[48] </D> 
		 <D ID="17">  C[51] </D> 
		 <D ID="18">  C[54] </D> 
		 <D ID="19">  C[57] </D> 
		 <D ID="20">  C[60] </D> 
		 <D ID="21">  C[63] </D> 
		 <D ID="22">  C[66] </D> 
		 <D ID="23">  C[69] </D> 
		 <D ID="24">  C[72] </D> 
		 <D ID="25">  C[75] </D> 
		 <D ID="26">  C[78] </D> 
		 <D ID="27">  C[81] </D> 
		 <D ID="28">  C[84] </D> 
		 <D ID="29">  C[87] </D> 
		 <D ID="30">  C[90] </D> 
		 <D ID="31">  C[93] </D> 
		 <D ID="32">  C[96] </D> 
		 <D ID="33">  C[99] </D> 
		 <D ID="34"> C[102] </D> 
		 <D ID="35"> C[105] </D> 
		 <D ID="36"> C[108] </D> 
		 <D ID="37"> C[111] </D> 
		 <D ID="38"> C[114] </D> 
		 <D ID="39"> C[117] </D> 
		 <D ID="40"> C[120] </D> 
		 <D ID="41"> C[123] </D> 
		 <D ID="42"> C[126] </D> 
		 <D ID="43"> C[129] </D> 
		 <D ID="44"> C[132] </D> 
		 <D ID="45"> C[135] </D> 
		 <D ID="46"> C[138] </D> 
		 <D ID="47"> C[141] </D> 
		 <D ID="48"> C[144] </D> 
		 <D ID="49"> C[147] </D> 
		 <D ID="50"> C[150] </D> 
		 <D ID="51"> C[153] </D> 
		 <D ID="52"> C[156] </D> 
		 <D ID="53"> C[159] </D> 
		 <D ID="54"> C[162] </D> 
	 </DOMAIN> 

</GEOMETRY> 

<EXPANSIONS> 
	 <E COMPOSITE="C[0]"   NUMMODES="4" FIELDS="A, u" TYPE="MODIFIED" /> 
	 <E COMPOSITE="C[3]"   NUMMODES="4" FIELDS="A, u" TYPE="MODIFIED" /> 
	 <E COMPOSITE="C[6]"   NUMMODES="4" FIELDS="A, u" TYPE="MODIFIED" /> 
	 <E COMPOSITE="C[9]"   NUMMODES="4" FIELDS="A, u" TYPE="MODIFIED" /> 
	 <E COMPOSITE="C[12]"  NUMMODES="4" FIELDS="A, u" TYPE="MODIFIED" /> 
	 <E COMPOSITE="C[15]"  NUMMODES="4" FIELDS="A, u" TYPE="MODIFIED" /> 
	 <E COMPOSITE="C[18]"  NUMMODES="4" FIELDS="A, u" TYPE="MODIFIED" /> 
	 <E COMPOSITE="C[21]"  NUMMODES="4" FIELDS="A, u" TYPE="MODIFIED" /> 
	 <E COMPOSITE="C[24]"  NUMMODES="4" FIELDS="A, u" TYPE="MODIFIED" /> 
	 <E COMPOSITE="C[27]"  NUMMODES="4" FIELDS="A, u" TYPE="MODIFIED" /> 
	 <E COMPOSITE="C[30]"  NUMMODES="4" FIELDS="A, u" TYPE="MODIFIED" /> 
	 <E COMPOSITE="C[33]"  NUMMODES="4" FIELDS="A, u" TYPE="MODIFIED" /> 
	 <E COMPOSITE="C[36]"  NUMMODES="4" FIELDS="A, u" TYPE="MODIFIED" /> 
	 <E COMPOSITE="C[39]"  NUMMODES="4" FIELDS="A, u" TYPE="MODIFIED" /> 
	 <E COMPOSITE="C[42]"  NUMMODES="4" FIELDS="A, u" TYPE="MODIFIED" /> 
	 <E COMPOSITE="C[45]"  NUMMODES="4" FIELDS="A, u" TYPE="MODIFIED" /> 
	 <E COMPOSITE="C[48]"  NUMMODES="4" FIELDS="A, u" TYPE="MODIFIED" /> 
	 <E COMPOSITE="C[51]"  NUMMODES="4" FIELDS="A, u" TYPE="MODIFIED" /> 
	 <E COMPOSITE="C[54]"  NUMMODES="4" FIELDS="A, u" TYPE="MODIFIED" /> 
	 <E COMPOSITE="C[57]"  NUMMODES="4" FIELDS="A, u" TYPE="MODIFIED" /> 
	 <E COMPOSITE="C[60]"  NUMMODES="4" FIELDS="A, u" TYPE="MODIFIED" /> 
	 <E COMPOSITE="C[63]"  NUMMODES="4" FIELDS="A, u" TYPE="MODIFIED" /> 
	 <E COMPOSITE="C[66]"  NUMMODES="4" FIELDS="A, u" TYPE="MODIFIED" /> 
	 <E COMPOSITE="C[69]"  NUMMODES="4" FIELDS="A, u" TYPE="MODIFIED" /> 
	 <E COMPOSITE="C[72]"  NUMMODES="4" FIELDS="A, u" TYPE="MODIFIED" /> 
	 <E COMPOSITE="C[75]"  NUMMODES="4" FIELDS="A, u" TYPE="MODIFIED" /> 
	 <E COMPOSITE="C[78]"  NUMMODES="4" FIELDS="A, u" TYPE="MODIFIED" /> 
	 <E COMPOSITE="C[81]"  NUMMODES="4" FIELDS="A, u" TYPE="MODIFIED" /> 
	 <E COMPOSITE="C[84]"  NUMMODES="4" FIELDS="A, u" TYPE="MODIFIED" /> 
	 <E COMPOSITE="C[87]"  NUMMODES="4" FIELDS="A, u" TYPE="MODIFIED" /> 
	 <E COMPOSITE="C[90]"  NUMMODES="4" FIELDS="A, u" TYPE="MODIFIED" /> 
	 <E COMPOSITE="C[93]"  NUMMODES="4" FIELDS="A, u" TYPE="MODIFIED" /> 
	 <E COMPOSITE="C[96]"  NUMMODES="4" FIELDS="A, u" TYPE="MODIFIED" /> 
	 <E COMPOSITE="C[99]"  NUMMODES="4" FIELDS="A, u" TYPE="MODIFIED" /> 
	 <E COMPOSITE="C[102]" NUMMODES="4" FIELDS="A, u" TYPE="MODIFIED" /> 
	 <E COMPOSITE="C[105]" NUMMODES="4" FIELDS="A, u" TYPE="MODIFIED" /> 
	 <E COMPOSITE="C[108]" NUMMODES="4" FIELDS="A, u" TYPE="MODIFIED" /> 
	 <E COMPOSITE="C[111]" NUMMODES="4" FIELDS="A, u" TYPE="MODIFIED" /> 
	 <E COMPOSITE="C[114]" NUMMODES="4" FIELDS="A, u" TYPE="MODIFIED" /> 
	 <E COMPOSITE="C[117]" NUMMODES="4" FIELDS="A, u" TYPE="MODIFIED" /> 
	 <E COMPOSITE="C[120]" NUMMODES="4" FIELDS="A, u" TYPE="MODIFIED" /> 
	 <E COMPOSITE="C[123]" NUMMODES="4" FIELDS="A, u" TYPE="MODIFIED" /> 
	 <E COMPOSITE="C[126]" NUMMODES="4" FIELDS="A, u" TYPE="MODIFIED" /> 
	 <E COMPOSITE="C[129]" NUMMODES="4" FIELDS="A, u" TYPE="MODIFIED" /> 
	 <E COMPOSITE="C[132]" NUMMODES="4" FIELDS="A, u" TYPE="MODIFIED" /> 
	 <E COMPOSITE="C[135]" NUMMODES="4" FIELDS="A, u" TYPE="MODIFIED" /> 
	 <E COMPOSITE="C[138]" NUMMODES="4" FIELDS="A, u" TYPE="MODIFIED" /> 
	 <E COMPOSITE="C[141]" NUMMODES="4" FIELDS="A, u" TYPE="MODIFIED" /> 
	 <E COMPOSITE="C[144]" NUMMODES="4" FIELDS="A, u" TYPE="MODIFIED" /> 
	 <E COMPOSITE="C[147]" NUMMODES="4" FIELDS="A, u" TYPE="MODIFIED" /> 
	 <E COMPOSITE="C[150]" NUMMODES="4" FIELDS="A, u" TYPE="MODIFIED" /> 
	 <E COMPOSITE="C[153]" NUMMODES="4" FIELDS="A, u" TYPE="MODIFIED" /> 
	 <E COMPOSITE="C[156]" NUMMODES="4" FIELDS="A, u" TYPE="MODIFIED" /> 
	 <E COMPOSITE="C[159]" NUMMODES="4" FIELDS="A, u" TYPE="MODIFIED" /> 
	 <E COMPOSITE="C[162]" NUMMODES="4" FIELDS="A, u" TYPE="MODIFIED" /> 
</EXPANSIONS> 

<CONDITIONS> 

	 <PARAMETERS> 
		 <P> TimeStep = 1e-06 </P> 
		 <P> T = 0.9836065573770492 </P> 
		 <P> FinTime = 8 </P>
		 <P> NumSteps = FinTime / TimeStep </P> 
		 <P> IO_CheckSteps = NumSteps / 8000 </P>
		 <P> IO_InfoSteps = 1000 </P> 
		 <P> omega = 2 * PI / T </P> 
		 <P> rho = 0.00106 </P> 
		 <P> neu = 0.5 </P> 
		 <P> pext = 91.03026368811582 </P> 
		 <P> pout = 14.532019524968836 </P> 

		 <!--P> Age = 61 </P>
		 <P> Sex = M </P>
		 <P> EDV = 150.9344191134652 </P>
		 <P> EF = 0.643293923770659 </P>
		 <P> SV = 97.09519470354617 </P>
		 <P> LVET = 0.284556 </P>
		 <P> HR = 61 </P>
		 <P> CO = 5.922806876916317 </P>
		 <P> HF = 0 </P>
		 <P> a_elas = 1.7853915871474284 </P>
		 <P> a_musc = 1.2110439625579066 </P>
		 <P> D_elas = 1.1882392184256223 </P>
		 <P> D_musc = 1.1734563479624274 </P>
		 <P> Phi_scale = 0.900349513745593 </P>
		 <P> PExt = 0.9103026368811582 </P>
		 <P> R_scale = 1.5346679276175328 </P>
		 <P> C_scale = 1.0973756925591693 </P>
		 <P> R_HF = 1 </P>
		 <P> C_HF = 1 </P>
		 <P> POut_scale = 1.0901740078746314 </P-->
	 </PARAMETERS> 

	 <SOLVERINFO> 
		 <I PROPERTY="EQTYPE" VALUE="PulseWavePropagation" /> 
		 <I PROPERTY="Projection" VALUE="DisContinuous" /> 
		 <I PROPERTY="TimeIntegrationMethod" VALUE="RungeKutta2_ImprovedEuler" /> 
		 <I PROPERTY="UpwindTypePulse" VALUE="UpwindPulse" /> 
		 <I PROPERTY="PressureArea" VALUE="Empirical" /> 
		 <I PROPERTY="OutputExtraFields" VALUE="True" /> 
	 </SOLVERINFO> 

	 <VARIABLES> 
		 <V ID="0"> A </V> 
		 <V ID="1"> u </V> 
	 </VARIABLES> 

	 <BOUNDARYREGIONS> 
		 <B ID="0"> C[1] </B> 
		 <B ID="1"> C[17] </B> 
		 <B ID="2"> C[23] </B> 
		 <B ID="3"> C[29] </B> 
		 <B ID="4"> C[32] </B> 
		 <B ID="5"> C[35] </B> 
		 <B ID="6"> C[38] </B> 
		 <B ID="7"> C[47] </B> 
		 <B ID="8"> C[50] </B> 
		 <B ID="9"> C[59] </B> 
		 <B ID="10"> C[65] </B> 
		 <B ID="11"> C[71] </B> 
		 <B ID="12"> C[74] </B> 
		 <B ID="13"> C[77] </B> 
		 <B ID="14"> C[92] </B> 
		 <B ID="15"> C[95] </B> 
		 <B ID="16"> C[98] </B> 
		 <B ID="17"> C[101] </B> 
		 <B ID="18"> C[107] </B> 
		 <B ID="19"> C[113] </B> 
		 <B ID="20"> C[119] </B> 
		 <B ID="21"> C[134] </B> 
		 <B ID="22"> C[140] </B> 
		 <B ID="23"> C[143] </B> 
		 <B ID="24"> C[146] </B> 
		 <B ID="25"> C[152] </B> 
		 <B ID="26"> C[158] </B> 
		 <B ID="27"> C[161] </B> 
		 <B ID="28"> C[164] </B> 
	 </BOUNDARYREGIONS> 

	 <BOUNDARYCONDITIONS> 

		 <REGION REF="0">
			 <D VAR="A" USERDEFINEDTYPE="Q-inflow" VALUE="0.5 * 194.28339969297062 * cos(0 * PI * t / T) + 0.0 * sin(0 * PI * t / T) + 
                      0.006360822861535022 * cos(1  * PI * t / T) + -0.014072146478205174 * sin(1  * PI * t / T) +
                      117.33409701708862 * cos(2  * PI * t / T) + 139.8496398204426 * sin(2  * PI * t / T) + 
                      0.03749625659982559 * cos(3  * PI * t / T) + -0.01073879304905653 * sin(3  * PI * t / T) + 
                      -18.72945236350489 * cos(4  * PI * t / T) + 142.369640975999 * sin(4  * PI * t / T) + 
                      0.04029426702331031 * cos(5  * PI * t / T) + 0.025434837767169278 * sin(5  * PI * t / T) + 
                      -74.86117293408127 * cos(6  * PI * t / T) + 52.63681152360607 * sin(6  * PI * t / T) + 
                      0.009188238764600959 * cos(7  * PI * t / T) + 0.036411429475707816 * sin(7  * PI * t / T) + 
                      -43.06325479462402 * cos(8  * PI * t / T) + -3.9362634538698904 * sin(8  * PI * t / T) + 
                      -0.003344523533427555 * cos(9  * PI * t / T) + 0.016834882505950725 * sin(9  * PI * t / T) + 
                      -14.961587300304044 * cos(10 * PI * t / T) + 1.142057678234456 * sin(10 * PI * t / T) + 
                      0.0061915106525475576 * cos(11 * PI * t / T) + 0.012900031672625014 * sin(11 * PI * t / T) + 
                      -20.086629349279242 * cos(12 * PI * t / T) + 6.370995728704609 * sin(12 * PI * t / T) + 
                      -0.0003053368537112309 * cos(13 * PI * t / T) + 0.02198373368090331 * sin(13 * PI * t / T) + 
                      -17.69986756733313 * cos(14 * PI * t / T) + -5.904701335905286 * sin(14 * PI * t / T) + 
                      -0.010385161968741077 * cos(15 * PI * t / T) + 0.013733733452825251 * sin(15 * PI * t / T) + 
                      -5.851459657977006 * cos(16 * PI * t / T) + -6.582440276793248 * sin(16 * PI * t / T) + 
                      -0.0036103742943894746 * cos(17 * PI * t / T) + 0.005638552292895782 * sin(17 * PI * t / T) + 
                      -6.020644186499056 * cos(18 * PI * t / T) + -0.009428315999772714 * sin(18 * PI * t / T) + 
                      -0.0018583433790096446 * cos(19 * PI * t / T) + 0.013467791788226852 * sin(19 * PI * t / T) + 
                      -9.064082146460505 * cos(20 * PI * t / T) + -4.660646169098071 * sin(20 * PI * t / T) + 
                      -0.01284860734357314 * cos(21 * PI * t / T) + 0.010702900127385815 * sin(21 * PI * t / T) + 
                      -1.8257195329254774 * cos(22 * PI * t / T) + -7.713346651481289 * sin(22 * PI * t / T) + 
                      -0.008442273727120843 * cos(23 * PI * t / T) + -0.0015136404962394696 * sin(23 * PI * t / T) + 
                      0.48822480046007566 * cos(24 * PI * t / T) + -1.256934492332821 * sin(24 * PI * t / T) + 
                      0.0006321710909456763 * cos(25 * PI * t / T) + 0.004411089299000074 * sin(25 * PI * t / T) + 
                      -4.676448202837718 * cos(26 * PI * t / T) + -1.3607936040353372 * sin(26 * PI * t / T) + 
                      -0.009248769200958738 * cos(27 * PI * t / T) + 0.010101086494033358 * sin(27 * PI * t / T) + 
                      -2.2344750346179114 * cos(28 * PI * t / T) + -6.652637283725458 * sin(28 * PI * t / T) + 
                      -0.01424104027382597 * cos(29 * PI * t / T) + -0.0036724198192768565 * sin(29 * PI * t / T) + 
                      3.4548313623264706 * cos(30 * PI * t / T) + -3.1865977502609506 * sin(30 * PI * t / T) + 
                      -0.0004613796686704326 * cos(31 * PI * t / T) + -0.007241618066834112 * sin(31 * PI * t / T) + 
                      0.42389360898128725 * cos(32 * PI * t / T) + 1.3372007478635655 * sin(32 * PI * t / T) + 
                      0.00032942342232011195 * cos(33 * PI * t / T) + 0.00492034539318696 * sin(33 * PI * t / T) + 
                      -2.0428423994633946 * cos(34 * PI * t / T) + -2.0776349181530773 * sin(34 * PI * t / T) + 
                      -0.009849713922345862 * cos(35 * PI * t / T) + 0.001089844862388086 * sin(35 * PI * t / T) + 
                      1.804532659805815 * cos(36 * PI * t / T) + -2.9784185379220602 * sin(36 * PI * t / T) + 
                      -0.003166748715867424 * cos(37 * PI * t / T) + -0.007992735651856786 * sin(37 * PI * t / T) + 
                      1.9600407811216183 * cos(38 * PI * t / T) + 0.8350921793664353 * sin(38 * PI * t / T) + 
                      0.004078350250945122 * cos(39 * PI * t / T) + -2.0311288350185305e-05 * sin(39 * PI * t / T) + 
                      -1.188860380201155 * cos(40 * PI * t / T) + 0.04627242238365436 * sin(40 * PI * t / T) + 
                      -0.004750178664392667 * cos(41 * PI * t / T) + 0.002857291717534575 * sin(41 * PI * t / T) +   
                      0.6340590600856267 * cos(42 * PI * t / T) + -2.088507691761819 * sin(42 * PI * t / T) + 
                      -0.003661469222501829 * cos(43 * PI * t / T) + -0.00703374422633199 * sin(43 * PI * t / T) +   
                      2.078490048122751 * cos(44 * PI * t / T) + 0.6129448132763751 * sin(44 * PI * t / T) + 
                      0.006386571169607887 * cos(45 * PI * t / T) + -0.003070440641000013 * sin(45 * PI * t / T) +   
                      -0.8426808247540589 * cos(46 * PI * t / T) + 1.5053805171532457 * sin(46 * PI * t / T) + 
                      0.0004041137123496927 * cos(47 * PI * t / T) + 0.0057827247637526604 * sin(47 * PI * t / T) +   
                      -0.9641382130147145 * cos(48 * PI * t / T) + -1.2087362435279554 * sin(48 * PI * t / T) + 
                      -0.0059592373079096215 * cos(49 * PI * t / T) + -0.0017998054756380123 * sin(49 * PI * t / T) +   
                      1.424631450706469 * cos(50 * PI * t / T) + -0.5266822094588516 * sin(50 * PI * t / T) + 
                      0.0027798340997556297 * cos(51 * PI * t / T) + -0.005051420614785975 * sin(51 * PI * t / T) +   
                      0.24153314454657124 * cos(52 * PI * t / T) + 1.3259133073087153 * sin(52 * PI * t / T) + 
                      0.0037358994426547436 * cos(53 * PI * t / T) + 0.0036490233314603643 * sin(53 * PI * t / T) +   
                      -1.082659894365635 * cos(54 * PI * t / T) + -0.18941093041706128 * sin(54 * PI * t / T) + 
                      -0.0041488977445115266 * cos(55 * PI * t / T) + 0.0017098698040816454 * sin(55 * PI * t / T) +   
                      0.6134051656643226 * cos(56 * PI * t / T) + -0.7840660029139362 * sin(56 * PI * t / T) + 
                      0.0004798548405421263 * cos(57 * PI * t / T) + -0.004630890605824018 * sin(57 * PI * t / T) +   
                      0.5736587362367851 * cos(58 * PI * t / T) + 0.9663074574473515 * sin(58 * PI * t / T) + 
                      0.005355943465441607 * cos(59 * PI * t / T) + 0.0020280371889340064 * sin(59 * PI * t / T) +   
                      -1.127625793157415 * cos(60 * PI * t / T) + 0.4334513546776202 * sin(60 * PI * t / T) + 
                      -0.0023895066487721545 * cos(61 * PI * t / T) + 0.005123987647870494 * sin(61 * PI * t / T) +  
                      -0.26867630461774505 * cos(62 * PI * t / T) + -1.042838264303064 * sin(62 * PI * t / T) + 
                      -0.0034827277289021935 * cos(63 * PI * t / T) + -0.00305689540732729 * sin(63 * PI * t / T) +  
                      0.8157474745606094 * cos(64 * PI * t / T) + 0.10794093368990765 * sin(64 * PI * t / T) + 
                      0.004092310547012428 * cos(65 * PI * t / T) + -0.001981069907033681 * sin(65 * PI * t / T) +  
                      -0.48013255769672303 * cos(66 * PI * t / T) + 0.822702316983148 * sin(66 * PI * t / T) + 
                      0.0008648757489694673 * cos(67 * PI * t / T) + 0.004937293987873234 * sin(67 * PI * t / T) +  
                      -0.7382494572692655 * cos(68 * PI * t / T) + -0.5115260866856641 * sin(68 * PI * t / T) + 
                      -0.004538247771504363 * cos(69 * PI * t / T) + 0.00048531776006761413 * sin(69 * PI * t / T) +  
                      0.5049796883987225 * cos(70 * PI * t / T) + -0.45540246517902727 * sin(70 * PI * t / T)"/> 
			 <D VAR="u" USERDEFINEDTYPE="Q-inflow" VALUE="1.0" /> 
		 </REGION> 

		 <REGION REF="1"> 
			 <D VAR="A" USERDEFINEDTYPE="RCR-terminal"  VALUE="69.21352353555073" /> 
			 <D VAR="u" USERDEFINEDTYPE="RCR-terminal"  VALUE="0.009898328746883707" /> 
		 </REGION> 

		 <REGION REF="2"> 
			 <D VAR="A" USERDEFINEDTYPE="RCR-terminal"  VALUE="60.7728499336543" /> 
			 <D VAR="u" USERDEFINEDTYPE="RCR-terminal"  VALUE="0.010831098085559002" /> 
		 </REGION> 

		 <REGION REF="3"> 
			 <D VAR="A" USERDEFINEDTYPE="RCR-terminal"  VALUE="969.9101302542807" /> 
			 <D VAR="u" USERDEFINEDTYPE="RCR-terminal"  VALUE="0.0035664710008173" /> 
		 </REGION> 

		 <REGION REF="4"> 
			 <D VAR="A" USERDEFINEDTYPE="RCR-terminal"  VALUE="60.7728499336543" /> 
			 <D VAR="u" USERDEFINEDTYPE="RCR-terminal"  VALUE="0.008438819075780013" /> 
		 </REGION> 

		 <REGION REF="5"> 
			 <D VAR="A" USERDEFINEDTYPE="RCR-terminal"  VALUE="28.851757039209616" /> 
			 <D VAR="u" USERDEFINEDTYPE="RCR-terminal"  VALUE="0.02831229286802657" /> 
		 </REGION> 

		 <REGION REF="6"> 
			 <D VAR="A" USERDEFINEDTYPE="RCR-terminal"  VALUE="159.60546447222342" /> 
			 <D VAR="u" USERDEFINEDTYPE="RCR-terminal"  VALUE="0.021179350866391968" /> 
		 </REGION> 

		 <REGION REF="7"> 
			 <D VAR="A" USERDEFINEDTYPE="RCR-terminal"  VALUE="28.851757039209616" /> 
			 <D VAR="u" USERDEFINEDTYPE="RCR-terminal"  VALUE="0.0207404005893683" /> 
		 </REGION> 

		 <REGION REF="8"> 
			 <D VAR="A" USERDEFINEDTYPE="RCR-terminal"  VALUE="159.60546447222342" /> 
			 <D VAR="u" USERDEFINEDTYPE="RCR-terminal"  VALUE="0.01898459948127363" /> 
		 </REGION> 

		 <REGION REF="9"> 
			 <D VAR="A" USERDEFINEDTYPE="RCR-terminal"  VALUE="69.21352353555073" /> 
			 <D VAR="u" USERDEFINEDTYPE="RCR-terminal"  VALUE="0.009898328746883707" /> 
		 </REGION> 

		 <REGION REF="10"> 
			 <D VAR="A" USERDEFINEDTYPE="RCR-terminal"  VALUE="60.7728499336543" /> 
			 <D VAR="u" USERDEFINEDTYPE="RCR-terminal"  VALUE="0.009305745872901755" /> 
		 </REGION> 

		 <REGION REF="11"> 
			 <D VAR="A" USERDEFINEDTYPE="RCR-terminal"  VALUE="969.9101302542807" /> 
			 <D VAR="u" USERDEFINEDTYPE="RCR-terminal"  VALUE="0.003039730668388899" /> 
		 </REGION> 

		 <REGION REF="12"> 
			 <D VAR="A" USERDEFINEDTYPE="RCR-terminal"  VALUE="60.7728499336543" /> 
			 <D VAR="u" USERDEFINEDTYPE="RCR-terminal"  VALUE="0.0142658840032692" /> 
		 </REGION> 

		 <REGION REF="13"> 
			 <D VAR="A" USERDEFINEDTYPE="RCR-terminal"  VALUE="92.08007565705196" /> 
			 <D VAR="u" USERDEFINEDTYPE="RCR-terminal"  VALUE="0.1141270720261536" /> 
		 </REGION> 

		 <REGION REF="14"> 
			 <D VAR="A" USERDEFINEDTYPE="RCR-terminal"  VALUE="41.74296763119689" /> 
			 <D VAR="u" USERDEFINEDTYPE="RCR-terminal"  VALUE="0.022496201697462973" /> 
		 </REGION> 

		 <REGION REF="15"> 
			 <D VAR="A" USERDEFINEDTYPE="RCR-terminal"  VALUE="62.30751786127183" /> 
			 <D VAR="u" USERDEFINEDTYPE="RCR-terminal"  VALUE="0.00900945443591078" /> 
		 </REGION> 

		 <REGION REF="16"> 
			 <D VAR="A" USERDEFINEDTYPE="RCR-terminal"  VALUE="26.703221940545067" /> 
			 <D VAR="u" USERDEFINEDTYPE="RCR-terminal"  VALUE="0.015363259695828371" /> 
		 </REGION> 

		 <REGION REF="17"> 
			 <D VAR="A" USERDEFINEDTYPE="RCR-terminal"  VALUE="10.711982134770379" /> 
			 <D VAR="u" USERDEFINEDTYPE="RCR-terminal"  VALUE="0.052783770812096044" /> 
		 </REGION> 

		 <REGION REF="18"> 
			 <D VAR="A" USERDEFINEDTYPE="RCR-terminal"  VALUE="13.01398402619668" /> 
			 <D VAR="u" USERDEFINEDTYPE="RCR-terminal"  VALUE="0.02534937849811681" /> 
		 </REGION> 

		 <REGION REF="19"> 
			 <D VAR="A" USERDEFINEDTYPE="RCR-terminal"  VALUE="13.01398402619668" /> 
			 <D VAR="u" USERDEFINEDTYPE="RCR-terminal"  VALUE="0.02534937849811681" /> 
		 </REGION> 

		 <REGION REF="20"> 
			 <D VAR="A" USERDEFINEDTYPE="RCR-terminal"  VALUE="79.18886506506469" /> 
			 <D VAR="u" USERDEFINEDTYPE="RCR-terminal"  VALUE="0.014595096711036952" /> 
		 </REGION> 

		 <REGION REF="21"> 
			 <D VAR="A" USERDEFINEDTYPE="RCR-terminal"  VALUE="91.46620848600496" /> 
			 <D VAR="u" USERDEFINEDTYPE="RCR-terminal"  VALUE="0.01503404698806062" /> 
		 </REGION> 

		 <REGION REF="22"> 
			 <D VAR="A" USERDEFINEDTYPE="RCR-terminal"  VALUE="54.94111180870767" /> 
			 <D VAR="u" USERDEFINEDTYPE="RCR-terminal"  VALUE="0.01393667129550145" /> 
		 </REGION> 

		 <REGION REF="23"> 
			 <D VAR="A" USERDEFINEDTYPE="RCR-terminal"  VALUE="162.67480032745848" /> 
			 <D VAR="u" USERDEFINEDTYPE="RCR-terminal"  VALUE="0.008153501395714628" /> 
		 </REGION> 

		 <REGION REF="24"> 
			 <D VAR="A" USERDEFINEDTYPE="RCR-terminal"  VALUE="162.67480032745848" /> 
			 <D VAR="u" USERDEFINEDTYPE="RCR-terminal"  VALUE="0.005629537302828539" /> 
		 </REGION> 

		 <REGION REF="25"> 
			 <D VAR="A" USERDEFINEDTYPE="RCR-terminal"  VALUE="91.46620848600496" /> 
			 <D VAR="u" USERDEFINEDTYPE="RCR-terminal"  VALUE="0.01503404698806062" /> 
		 </REGION> 

		 <REGION REF="26"> 
			 <D VAR="A" USERDEFINEDTYPE="RCR-terminal"  VALUE="54.94111180870767" /> 
			 <D VAR="u" USERDEFINEDTYPE="RCR-terminal"  VALUE="0.01393667129550145" /> 
		 </REGION> 

		 <REGION REF="27"> 
			 <D VAR="A" USERDEFINEDTYPE="RCR-terminal"  VALUE="162.67480032745848" /> 
			 <D VAR="u" USERDEFINEDTYPE="RCR-terminal"  VALUE="0.008153501395714628" /> 
		 </REGION> 

		 <REGION REF="28"> 
			 <D VAR="A" USERDEFINEDTYPE="RCR-terminal"  VALUE="162.67480032745848" /> 
			 <D VAR="u" USERDEFINEDTYPE="RCR-terminal"  VALUE="0.005629537302828539" /> 
		 </REGION> 

	 </BOUNDARYCONDITIONS> 

		<FUNCTION NAME="InitialConditions"> 
				<E VAR="A" DOMAIN="0"  VALUE="10.1808 * (1 - 0.00115242 * (x - 0))" /> 
				<E VAR="u" DOMAIN="0"  VALUE="0.0" /> 
				<E VAR="A" DOMAIN="1"  VALUE="7.38137 * (1 - 0.0368031 * (x - 5.71822))" /> 
				<E VAR="u" DOMAIN="1"  VALUE="0.0" /> 
				<E VAR="A" DOMAIN="2"  VALUE="4.7976 * (1 - 0.0543371 * (x - 5.71822))" /> 
				<E VAR="u" DOMAIN="2"  VALUE="0.0" /> 
				<E VAR="A" DOMAIN="3"  VALUE="1.54405 * (1 - 0.0995689 * (x - 9.56322))" /> 
				<E VAR="u" DOMAIN="3"  VALUE="0.0" /> 
				<E VAR="A" DOMAIN="4"  VALUE="1.41597 * (1 - 0.0686599 * (x - 9.56322))" /> 
				<E VAR="u" DOMAIN="4"  VALUE="0.0" /> 
				<E VAR="A" DOMAIN="5"  VALUE="0.160971 * (1 - 0.0254232 * (x - 13.4082))" /> 
				<E VAR="u" DOMAIN="5"  VALUE="0.0" /> 
				<E VAR="A" DOMAIN="6"  VALUE="0.771311 * (1 - 0.01387 * (x - 13.4082))" /> 
				<E VAR="u" DOMAIN="6"  VALUE="0.0" /> 
				<E VAR="A" DOMAIN="7"  VALUE="0.160971 * (1 - 0.0112316 * (x - 61.2243))" /> 
				<E VAR="u" DOMAIN="7"  VALUE="0.0" /> 
				<E VAR="A" DOMAIN="8"  VALUE="0.160971 * (1 - 0.0205639 * (x - 61.2243))" /> 
				<E VAR="u" DOMAIN="8"  VALUE="0.0" /> 
				<E VAR="A" DOMAIN="9"  VALUE="0.0517375 * (1 - 0.0296978 * (x - 68.8158))" /> 
				<E VAR="u" DOMAIN="9"  VALUE="0.0" /> 
				<E VAR="A" DOMAIN="10"  VALUE="0.12003 * (1 - 0.0120331 * (x - 68.8158))" /> 
				<E VAR="u" DOMAIN="10"  VALUE="0.0" /> 
				<E VAR="A" DOMAIN="11"  VALUE="0.382097 * (1 - 0.021425 * (x - 20.2109))" /> 
				<E VAR="u" DOMAIN="11"  VALUE="0.0" /> 
				<E VAR="A" DOMAIN="12"  VALUE="0.0732426 * (1 - 0.0347647 * (x - 20.2109))" /> 
				<E VAR="u" DOMAIN="12"  VALUE="0.0" /> 
				<E VAR="A" DOMAIN="13"  VALUE="5.36714 * (1 - 0.0121269 * (x - 7.98578))" /> 
				<E VAR="u" DOMAIN="13"  VALUE="0.0" /> 
				<E VAR="A" DOMAIN="14"  VALUE="1.10891 * (1 - 0.0474184 * (x - 7.98578))" /> 
				<E VAR="u" DOMAIN="14"  VALUE="0.0" /> 
				<E VAR="A" DOMAIN="15"  VALUE="0.217623 * (1 - 0.0198166 * (x - 23.7602))" /> 
				<E VAR="u" DOMAIN="15"  VALUE="0.0" /> 
				<E VAR="A" DOMAIN="16"  VALUE="0.0430358 * (1 - 0.0320519 * (x - 23.7602))" /> 
				<E VAR="u" DOMAIN="16"  VALUE="0.0" /> 
				<E VAR="A" DOMAIN="17"  VALUE="4.70579 * (1 - 0.0175719 * (x - 12.4223))" /> 
				<E VAR="u" DOMAIN="17"  VALUE="0.0" /> 
				<E VAR="A" DOMAIN="18"  VALUE="1.41597 * (1 - 0.106974 * (x - 12.4223))" /> 
				<E VAR="u" DOMAIN="18"  VALUE="0.0" /> 
				<E VAR="A" DOMAIN="19"  VALUE="0.160971 * (1 - 0.0255728 * (x - 16.2673))" /> 
				<E VAR="u" DOMAIN="19"  VALUE="0.0" /> 
				<E VAR="A" DOMAIN="20"  VALUE="0.771311 * (1 - 0.01387 * (x - 16.2673))" /> 
				<E VAR="u" DOMAIN="20"  VALUE="0.0" /> 
				<E VAR="A" DOMAIN="21"  VALUE="0.143715 * (1 - 0.013524 * (x - 64.0835))" /> 
				<E VAR="u" DOMAIN="21"  VALUE="0.0" /> 
				<E VAR="A" DOMAIN="22"  VALUE="0.217623 * (1 - 0 * (x - 64.0835))" /> 
				<E VAR="u" DOMAIN="22"  VALUE="0.0" /> 
				<E VAR="A" DOMAIN="23"  VALUE="0.0379526 * (1 - 0 * (x - 71.6749))" /> 
				<E VAR="u" DOMAIN="23"  VALUE="0.0" /> 
				<E VAR="A" DOMAIN="24"  VALUE="0.19748 * (1 - 0.00951866 * (x - 71.6749))" /> 
				<E VAR="u" DOMAIN="24"  VALUE="0.0" /> 
				<E VAR="A" DOMAIN="25"  VALUE="1.87406 * (1 - 0.0478523 * (x - 18.3377))" /> 
				<E VAR="u" DOMAIN="25"  VALUE="0.0" /> 
				<E VAR="A" DOMAIN="26"  VALUE="3.20476 * (1 - 0.0327893 * (x - 18.3377))" /> 
				<E VAR="u" DOMAIN="26"  VALUE="0.0" /> 
				<E VAR="A" DOMAIN="27"  VALUE="1.76051 * (1 - 0 * (x - 30.1685))" /> 
				<E VAR="u" DOMAIN="27"  VALUE="0.0" /> 
				<E VAR="A" DOMAIN="28"  VALUE="0.715037 * (1 - 0.0962344 * (x - 30.1685))" /> 
				<E VAR="u" DOMAIN="28"  VALUE="0.0" /> 
				<E VAR="A" DOMAIN="29"  VALUE="0.317399 * (1 - 0.049626 * (x - 32.4361))" /> 
				<E VAR="u" DOMAIN="29"  VALUE="0.0" /> 
				<E VAR="A" DOMAIN="30"  VALUE="0.342805 * (1 - 0.0448676 * (x - 32.4361))" /> 
				<E VAR="u" DOMAIN="30"  VALUE="0.0" /> 
				<E VAR="A" DOMAIN="31"  VALUE="0.12003 * (1 - 0.0145818 * (x - 34.7037))" /> 
				<E VAR="u" DOMAIN="31"  VALUE="0.0" /> 
				<E VAR="A" DOMAIN="32"  VALUE="0.20695 * (1 - 0.0188866 * (x - 34.7037))" /> 
				<E VAR="u" DOMAIN="32"  VALUE="0.0" /> 
				<E VAR="A" DOMAIN="33"  VALUE="0.732957 * (1 - 0.0285719 * (x - 36.1825))" /> 
				<E VAR="u" DOMAIN="33"  VALUE="0.0" /> 
				<E VAR="A" DOMAIN="34"  VALUE="1.54405 * (1 - 0.0148225 * (x - 36.1825))" /> 
				<E VAR="u" DOMAIN="34"  VALUE="0.0" /> 
				<E VAR="A" DOMAIN="35"  VALUE="0.317399 * (1 - 0 * (x - 38.4501))" /> 
				<E VAR="u" DOMAIN="35"  VALUE="0.0" /> 
				<E VAR="A" DOMAIN="36"  VALUE="1.62356 * (1 - 0 * (x - 38.4501))" /> 
				<E VAR="u" DOMAIN="36"  VALUE="0.0" /> 
				<E VAR="A" DOMAIN="37"  VALUE="0.317399 * (1 - 0 * (x - 40.7176))" /> 
				<E VAR="u" DOMAIN="37"  VALUE="0.0" /> 
				<E VAR="A" DOMAIN="38"  VALUE="1.57033 * (1 - 0.00817246 * (x - 40.7176))" /> 
				<E VAR="u" DOMAIN="38"  VALUE="0.0" /> 
				<E VAR="A" DOMAIN="39"  VALUE="0.25977 * (1 - 0.0945648 * (x - 52.7456))" /> 
				<E VAR="u" DOMAIN="39"  VALUE="0.0" /> 
				<E VAR="A" DOMAIN="40"  VALUE="1.36629 * (1 - 0.0312112 * (x - 52.7456))" /> 
				<E VAR="u" DOMAIN="40"  VALUE="0.0" /> 
				<E VAR="A" DOMAIN="41"  VALUE="0.714833 * (1 - 0.0321738 * (x - 55.0132))" /> 
				<E VAR="u" DOMAIN="41"  VALUE="0.0" /> 
				<E VAR="A" DOMAIN="42"  VALUE="0.714833 * (1 - 0.0321738 * (x - 55.0132))" /> 
				<E VAR="u" DOMAIN="42"  VALUE="0.0" /> 
				<E VAR="A" DOMAIN="43"  VALUE="0.469672 * (1 - 0.00561344 * (x - 61.7173))" /> 
				<E VAR="u" DOMAIN="43"  VALUE="0.0" /> 
				<E VAR="A" DOMAIN="44"  VALUE="0.183577 * (1 - 0 * (x - 61.7173))" /> 
				<E VAR="u" DOMAIN="44"  VALUE="0.0" /> 
				<E VAR="A" DOMAIN="45"  VALUE="0.30955 * (1 - 0.00928358 * (x - 78.0832))" /> 
				<E VAR="u" DOMAIN="45"  VALUE="0.0" /> 
				<E VAR="A" DOMAIN="46"  VALUE="0.183577 * (1 - 0.0101307 * (x - 78.0832))" /> 
				<E VAR="u" DOMAIN="46"  VALUE="0.0" /> 
				<E VAR="A" DOMAIN="47"  VALUE="0.110054 * (1 - 0.00508288 * (x - 128.265))" /> 
				<E VAR="u" DOMAIN="47"  VALUE="0.0" /> 
				<E VAR="A" DOMAIN="48"  VALUE="0.0776772 * (1 - 0.00555479 * (x - 128.265))" /> 
				<E VAR="u" DOMAIN="48"  VALUE="0.0" /> 
				<E VAR="A" DOMAIN="49"  VALUE="0.469672 * (1 - 0.00561344 * (x - 61.7173))" /> 
				<E VAR="u" DOMAIN="49"  VALUE="0.0" /> 
				<E VAR="A" DOMAIN="50"  VALUE="0.183577 * (1 - 0 * (x - 61.7173))" /> 
				<E VAR="u" DOMAIN="50"  VALUE="0.0" /> 
				<E VAR="A" DOMAIN="51"  VALUE="0.30955 * (1 - 0.00928358 * (x - 78.0832))" /> 
				<E VAR="u" DOMAIN="51"  VALUE="0.0" /> 
				<E VAR="A" DOMAIN="52"  VALUE="0.183577 * (1 - 0.0101307 * (x - 78.0832))" /> 
				<E VAR="u" DOMAIN="52"  VALUE="0.0" /> 
				<E VAR="A" DOMAIN="53"  VALUE="0.110054 * (1 - 0.00508288 * (x - 128.265))" /> 
				<E VAR="u" DOMAIN="53"  VALUE="0.0" /> 
				<E VAR="A" DOMAIN="54"  VALUE="0.0776772 * (1 - 0.00555479 * (x - 128.265))" /> 
				<E VAR="u" DOMAIN="54"  VALUE="0.0" /> 
		</FUNCTION> 

		<FUNCTION NAME="A_0"> 
				<E VAR="A_0" DOMAIN="0"  VALUE="10.1808 * (1 - 0.00115242 * (x - 0))" /> 
				<E VAR="A_0" DOMAIN="1"  VALUE="7.38137 * (1 - 0.0368031 * (x - 5.71822))" /> 
				<E VAR="A_0" DOMAIN="2"  VALUE="4.7976 * (1 - 0.0543371 * (x - 5.71822))" /> 
				<E VAR="A_0" DOMAIN="3"  VALUE="1.54405 * (1 - 0.0995689 * (x - 9.56322))" /> 
				<E VAR="A_0" DOMAIN="4"  VALUE="1.41597 * (1 - 0.0686599 * (x - 9.56322))" /> 
				<E VAR="A_0" DOMAIN="5"  VALUE="0.160971 * (1 - 0.0254232 * (x - 13.4082))" /> 
				<E VAR="A_0" DOMAIN="6"  VALUE="0.771311 * (1 - 0.01387 * (x - 13.4082))" /> 
				<E VAR="A_0" DOMAIN="7"  VALUE="0.160971 * (1 - 0.0112316 * (x - 61.2243))" /> 
				<E VAR="A_0" DOMAIN="8"  VALUE="0.160971 * (1 - 0.0205639 * (x - 61.2243))" /> 
				<E VAR="A_0" DOMAIN="9"  VALUE="0.0517375 * (1 - 0.0296978 * (x - 68.8158))" /> 
				<E VAR="A_0" DOMAIN="10"  VALUE="0.12003 * (1 - 0.0120331 * (x - 68.8158))" /> 
				<E VAR="A_0" DOMAIN="11"  VALUE="0.382097 * (1 - 0.021425 * (x - 20.2109))" /> 
				<E VAR="A_0" DOMAIN="12"  VALUE="0.0732426 * (1 - 0.0347647 * (x - 20.2109))" /> 
				<E VAR="A_0" DOMAIN="13"  VALUE="5.36714 * (1 - 0.0121269 * (x - 7.98578))" /> 
				<E VAR="A_0" DOMAIN="14"  VALUE="1.10891 * (1 - 0.0474184 * (x - 7.98578))" /> 
				<E VAR="A_0" DOMAIN="15"  VALUE="0.217623 * (1 - 0.0198166 * (x - 23.7602))" /> 
				<E VAR="A_0" DOMAIN="16"  VALUE="0.0430358 * (1 - 0.0320519 * (x - 23.7602))" /> 
				<E VAR="A_0" DOMAIN="17"  VALUE="4.70579 * (1 - 0.0175719 * (x - 12.4223))" /> 
				<E VAR="A_0" DOMAIN="18"  VALUE="1.41597 * (1 - 0.106974 * (x - 12.4223))" /> 
				<E VAR="A_0" DOMAIN="19"  VALUE="0.160971 * (1 - 0.0255728 * (x - 16.2673))" /> 
				<E VAR="A_0" DOMAIN="20"  VALUE="0.771311 * (1 - 0.01387 * (x - 16.2673))" /> 
				<E VAR="A_0" DOMAIN="21"  VALUE="0.143715 * (1 - 0.013524 * (x - 64.0835))" /> 
				<E VAR="A_0" DOMAIN="22"  VALUE="0.217623 * (1 - 0 * (x - 64.0835))" /> 
				<E VAR="A_0" DOMAIN="23"  VALUE="0.0379526 * (1 - 0 * (x - 71.6749))" /> 
				<E VAR="A_0" DOMAIN="24"  VALUE="0.19748 * (1 - 0.00951866 * (x - 71.6749))" /> 
				<E VAR="A_0" DOMAIN="25"  VALUE="1.87406 * (1 - 0.0478523 * (x - 18.3377))" /> 
				<E VAR="A_0" DOMAIN="26"  VALUE="3.20476 * (1 - 0.0327893 * (x - 18.3377))" /> 
				<E VAR="A_0" DOMAIN="27"  VALUE="1.76051 * (1 - 0 * (x - 30.1685))" /> 
				<E VAR="A_0" DOMAIN="28"  VALUE="0.715037 * (1 - 0.0962344 * (x - 30.1685))" /> 
				<E VAR="A_0" DOMAIN="29"  VALUE="0.317399 * (1 - 0.049626 * (x - 32.4361))" /> 
				<E VAR="A_0" DOMAIN="30"  VALUE="0.342805 * (1 - 0.0448676 * (x - 32.4361))" /> 
				<E VAR="A_0" DOMAIN="31"  VALUE="0.12003 * (1 - 0.0145818 * (x - 34.7037))" /> 
				<E VAR="A_0" DOMAIN="32"  VALUE="0.20695 * (1 - 0.0188866 * (x - 34.7037))" /> 
				<E VAR="A_0" DOMAIN="33"  VALUE="0.732957 * (1 - 0.0285719 * (x - 36.1825))" /> 
				<E VAR="A_0" DOMAIN="34"  VALUE="1.54405 * (1 - 0.0148225 * (x - 36.1825))" /> 
				<E VAR="A_0" DOMAIN="35"  VALUE="0.317399 * (1 - 0 * (x - 38.4501))" /> 
				<E VAR="A_0" DOMAIN="36"  VALUE="1.62356 * (1 - 0 * (x - 38.4501))" /> 
				<E VAR="A_0" DOMAIN="37"  VALUE="0.317399 * (1 - 0 * (x - 40.7176))" /> 
				<E VAR="A_0" DOMAIN="38"  VALUE="1.57033 * (1 - 0.00817246 * (x - 40.7176))" /> 
				<E VAR="A_0" DOMAIN="39"  VALUE="0.25977 * (1 - 0.0945648 * (x - 52.7456))" /> 
				<E VAR="A_0" DOMAIN="40"  VALUE="1.36629 * (1 - 0.0312112 * (x - 52.7456))" /> 
				<E VAR="A_0" DOMAIN="41"  VALUE="0.714833 * (1 - 0.0321738 * (x - 55.0132))" /> 
				<E VAR="A_0" DOMAIN="42"  VALUE="0.714833 * (1 - 0.0321738 * (x - 55.0132))" /> 
				<E VAR="A_0" DOMAIN="43"  VALUE="0.469672 * (1 - 0.00561344 * (x - 61.7173))" /> 
				<E VAR="A_0" DOMAIN="44"  VALUE="0.183577 * (1 - 0 * (x - 61.7173))" /> 
				<E VAR="A_0" DOMAIN="45"  VALUE="0.30955 * (1 - 0.00928358 * (x - 78.0832))" /> 
				<E VAR="A_0" DOMAIN="46"  VALUE="0.183577 * (1 - 0.0101307 * (x - 78.0832))" /> 
				<E VAR="A_0" DOMAIN="47"  VALUE="0.110054 * (1 - 0.00508288 * (x - 128.265))" /> 
				<E VAR="A_0" DOMAIN="48"  VALUE="0.0776772 * (1 - 0.00555479 * (x - 128.265))" /> 
				<E VAR="A_0" DOMAIN="49"  VALUE="0.469672 * (1 - 0.00561344 * (x - 61.7173))" /> 
				<E VAR="A_0" DOMAIN="50"  VALUE="0.183577 * (1 - 0 * (x - 61.7173))" /> 
				<E VAR="A_0" DOMAIN="51"  VALUE="0.30955 * (1 - 0.00928358 * (x - 78.0832))" /> 
				<E VAR="A_0" DOMAIN="52"  VALUE="0.183577 * (1 - 0.0101307 * (x - 78.0832))" /> 
				<E VAR="A_0" DOMAIN="53"  VALUE="0.110054 * (1 - 0.00508288 * (x - 128.265))" /> 
				<E VAR="A_0" DOMAIN="54"  VALUE="0.0776772 * (1 - 0.00555479 * (x - 128.265))" /> 
		</FUNCTION> 

		<FUNCTION NAME="MaterialProperties"> 
				<E VAR="beta" DOMAIN="0"  VALUE="504.401 * (1 + 0.000922543 * (x - 0))" /> 
				<E VAR="beta" DOMAIN="1"  VALUE="652.367 * (1 + 0.0296968 * (x - 5.71822))" /> 
				<E VAR="beta" DOMAIN="2"  VALUE="920.836 * (1 + 0.0444639 * (x - 5.71822))" /> 
				<E VAR="beta" DOMAIN="3"  VALUE="2280.72 * (1 + 0.0833032 * (x - 9.56322))" /> 
				<E VAR="beta" DOMAIN="4"  VALUE="2444.32 * (1 + 0.061073 * (x - 9.56322))" /> 
				<E VAR="beta" DOMAIN="5"  VALUE="16564.6 * (1 + 0.0214089 * (x - 13.4082))" /> 
				<E VAR="beta" DOMAIN="6"  VALUE="4729.28 * (1 + 0.0121573 * (x - 13.4082))" /> 
				<E VAR="beta" DOMAIN="7"  VALUE="16564.6 * (1 + 0.00929265 * (x - 61.2243))" /> 
				<E VAR="beta" DOMAIN="8"  VALUE="16564.6 * (1 + 0.0167255 * (x - 61.2243))" /> 
				<E VAR="beta" DOMAIN="9"  VALUE="41071 * (1 + 0.0244707 * (x - 68.8158))" /> 
				<E VAR="beta" DOMAIN="10"  VALUE="20948.2 * (1 + 0.0098757 * (x - 68.8158))" /> 
				<E VAR="beta" DOMAIN="11"  VALUE="8295.45 * (1 + 0.0180537 * (x - 20.2109))" /> 
				<E VAR="beta" DOMAIN="12"  VALUE="31100.5 * (1 + 0.030337 * (x - 20.2109))" /> 
				<E VAR="beta" DOMAIN="13"  VALUE="841.797 * (1 + 0.00975489 * (x - 7.98578))" /> 
				<E VAR="beta" DOMAIN="14"  VALUE="2972.24 * (1 + 0.0423477 * (x - 7.98578))" /> 
				<E VAR="beta" DOMAIN="15"  VALUE="13014.1 * (1 + 0.0166204 * (x - 23.7602))" /> 
				<E VAR="beta" DOMAIN="16"  VALUE="47589.9 * (1 + 0.0277086 * (x - 23.7602))" /> 
				<E VAR="beta" DOMAIN="17"  VALUE="935.182 * (1 + 0.0142101 * (x - 12.4223))" /> 
				<E VAR="beta" DOMAIN="18"  VALUE="2444.32 * (1 + 0.0898586 * (x - 12.4223))" /> 
				<E VAR="beta" DOMAIN="19"  VALUE="16564.6 * (1 + 0.0215349 * (x - 16.2673))" /> 
				<E VAR="beta" DOMAIN="20"  VALUE="4729.28 * (1 + 0.0121573 * (x - 16.2673))" /> 
				<E VAR="beta" DOMAIN="21"  VALUE="18137.5 * (1 + 0.0112794 * (x - 64.0835))" /> 
				<E VAR="beta" DOMAIN="22"  VALUE="13014.1 * (1 + 0 * (x - 64.0835))" /> 
				<E VAR="beta" DOMAIN="23"  VALUE="52624.3 * (1 + 0 * (x - 71.6749))" /> 
				<E VAR="beta" DOMAIN="24"  VALUE="14065.7 * (1 + 0.00776732 * (x - 71.6749))" /> 
				<E VAR="beta" DOMAIN="25"  VALUE="1953.32 * (1 + 0.0403285 * (x - 18.3377))" /> 
				<E VAR="beta" DOMAIN="26"  VALUE="1271.64 * (1 + 0.0274522 * (x - 18.3377))" /> 
				<E VAR="beta" DOMAIN="27"  VALUE="2053.48 * (1 + 0 * (x - 30.1685))" /> 
				<E VAR="beta" DOMAIN="28"  VALUE="4222.2 * (1 + 0.0788347 * (x - 30.1685))" /> 
				<E VAR="beta" DOMAIN="29"  VALUE="8085.7 * (1 + 0.040169 * (x - 32.4361))" /> 
				<E VAR="beta" DOMAIN="30"  VALUE="9047.76 * (1 + 0.0373015 * (x - 32.4361))" /> 
				<E VAR="beta" DOMAIN="31"  VALUE="20948.2 * (1 + 0.0118099 * (x - 34.7037))" /> 
				<E VAR="beta" DOMAIN="32"  VALUE="13548.4 * (1 + 0.0153236 * (x - 34.7037))" /> 
				<E VAR="beta" DOMAIN="33"  VALUE="4139.41 * (1 + 0.0233329 * (x - 36.1825))" /> 
				<E VAR="beta" DOMAIN="34"  VALUE="2280.72 * (1 + 0.0118984 * (x - 36.1825))" /> 
				<E VAR="beta" DOMAIN="35"  VALUE="8085.7 * (1 + 0 * (x - 38.4501))" /> 
				<E VAR="beta" DOMAIN="36"  VALUE="2190.92 * (1 + 0 * (x - 38.4501))" /> 
				<E VAR="beta" DOMAIN="37"  VALUE="8085.7 * (1 + 0 * (x - 40.7176))" /> 
				<E VAR="beta" DOMAIN="38"  VALUE="2250.14 * (1 + 0.00660491 * (x - 40.7176))" /> 
				<E VAR="beta" DOMAIN="39"  VALUE="11295.6 * (1 + 0.0810404 * (x - 52.7456))" /> 
				<E VAR="beta" DOMAIN="40"  VALUE="2515.17 * (1 + 0.0251509 * (x - 52.7456))" /> 
				<E VAR="beta" DOMAIN="41"  VALUE="3078.67 * (1 + 0.0263487 * (x - 55.0132))" /> 
				<E VAR="beta" DOMAIN="42"  VALUE="3078.67 * (1 + 0.0263487 * (x - 55.0132))" /> 
				<E VAR="beta" DOMAIN="43"  VALUE="4308.16 * (1 + 0.0045336 * (x - 61.7173))" /> 
				<E VAR="beta" DOMAIN="44"  VALUE="10941.1 * (1 + 0 * (x - 61.7173))" /> 
				<E VAR="beta" DOMAIN="45"  VALUE="7203.28 * (1 + 0.00786127 * (x - 78.0832))" /> 
				<E VAR="beta" DOMAIN="46"  VALUE="10941.1 * (1 + 0.00822934 * (x - 78.0832))" /> 
				<E VAR="beta" DOMAIN="47"  VALUE="16475.2 * (1 + 0.0041477 * (x - 128.265))" /> 
				<E VAR="beta" DOMAIN="48"  VALUE="21771.1 * (1 + 0.00455032 * (x - 128.265))" /> 
				<E VAR="beta" DOMAIN="49"  VALUE="4308.16 * (1 + 0.0045336 * (x - 61.7173))" /> 
				<E VAR="beta" DOMAIN="50"  VALUE="10941.1 * (1 + 0 * (x - 61.7173))" /> 
				<E VAR="beta" DOMAIN="51"  VALUE="7203.28 * (1 + 0.00786127 * (x - 78.0832))" /> 
				<E VAR="beta" DOMAIN="52"  VALUE="10941.1 * (1 + 0.00822934 * (x - 78.0832))" /> 
				<E VAR="beta" DOMAIN="53"  VALUE="16475.2 * (1 + 0.0041477 * (x - 128.265))" /> 
				<E VAR="beta" DOMAIN="54"  VALUE="21771.1 * (1 + 0.00455032 * (x - 128.265))" /> 
		</FUNCTION> 

		<FUNCTION NAME="Viscoelasticity"> 
				<E VAR="gamma" DOMAIN="0"  VALUE="0.101934 * (1 + 0.000693989 * (x - 0))" /> 
				<E VAR="gamma" DOMAIN="1"  VALUE="0.12343 * (1 + 0.0220383 * (x - 5.71822))" /> 
				<E VAR="gamma" DOMAIN="2"  VALUE="0.317652 * (1 + 0.0332798 * (x - 5.71822))" /> 
				<E VAR="gamma" DOMAIN="3"  VALUE="0.630679 * (1 + 0.0720243 * (x - 9.56322))" /> 
				<E VAR="gamma" DOMAIN="4"  VALUE="4.00355 * (1 + 0.0572292 * (x - 9.56322))" /> 
				<E VAR="gamma" DOMAIN="5"  VALUE="19.6022 * (1 + 0.0198226 * (x - 13.4082))" /> 
				<E VAR="gamma" DOMAIN="6"  VALUE="2.53224 * (1 + 0.0116299 * (x - 13.4082))" /> 
				<E VAR="gamma" DOMAIN="7"  VALUE="19.6022 * (1 + 0.00860572 * (x - 61.2243))" /> 
				<E VAR="gamma" DOMAIN="8"  VALUE="19.6022 * (1 + 0.0154936 * (x - 61.2243))" /> 
				<E VAR="gamma" DOMAIN="9"  VALUE="43.8619 * (1 + 0.0207629 * (x - 68.8158))" /> 
				<E VAR="gamma" DOMAIN="10"  VALUE="24.3145 * (1 + 0.00896524 * (x - 68.8158))" /> 
				<E VAR="gamma" DOMAIN="11"  VALUE="10.2223 * (1 + 0.0172643 * (x - 20.2109))" /> 
				<E VAR="gamma" DOMAIN="12"  VALUE="34.5595 * (1 + 0.0267934 * (x - 20.2109))" /> 
				<E VAR="gamma" DOMAIN="13"  VALUE="0.148767 * (1 + 0.00715513 * (x - 7.98578))" /> 
				<E VAR="gamma" DOMAIN="14"  VALUE="4.71416 * (1 + 0.0403251 * (x - 7.98578))" /> 
				<E VAR="gamma" DOMAIN="15"  VALUE="15.6474 * (1 + 0.0156432 * (x - 23.7602))" /> 
				<E VAR="gamma" DOMAIN="16"  VALUE="49.6136 * (1 + 0.0235693 * (x - 23.7602))" /> 
				<E VAR="gamma" DOMAIN="17"  VALUE="0.160626 * (1 + 0.0104885 * (x - 12.4223))" /> 
				<E VAR="gamma" DOMAIN="18"  VALUE="0.667258 * (1 + 0.0789945 * (x - 12.4223))" /> 
				<E VAR="gamma" DOMAIN="19"  VALUE="19.6022 * (1 + 0.0199392 * (x - 16.2673))" /> 
				<E VAR="gamma" DOMAIN="20"  VALUE="2.53224 * (1 + 0.0116299 * (x - 16.2673))" /> 
				<E VAR="gamma" DOMAIN="21"  VALUE="21.3146 * (1 + 0.0103693 * (x - 64.0835))" /> 
				<E VAR="gamma" DOMAIN="22"  VALUE="15.6474 * (1 + 0 * (x - 64.0835))" /> 
				<E VAR="gamma" DOMAIN="23"  VALUE="53.9027 * (1 + 0 * (x - 71.6749))" /> 
				<E VAR="gamma" DOMAIN="24"  VALUE="16.8314 * (1 + 0.00727763 * (x - 71.6749))" /> 
				<E VAR="gamma" DOMAIN="25"  VALUE="0.27873 * (1 + 0.0343698 * (x - 18.3377))" /> 
				<E VAR="gamma" DOMAIN="26"  VALUE="0.201196 * (1 + 0.0217446 * (x - 18.3377))" /> 
				<E VAR="gamma" DOMAIN="27"  VALUE="0.289939 * (1 + 0 * (x - 30.1685))" /> 
				<E VAR="gamma" DOMAIN="28"  VALUE="0.534845 * (1 + 0.0727612 * (x - 30.1685))" /> 
				<E VAR="gamma" DOMAIN="29"  VALUE="0.980287 * (1 + 0.0381336 * (x - 32.4361))" /> 
				<E VAR="gamma" DOMAIN="30"  VALUE="4.62371 * (1 + 0.0355765 * (x - 32.4361))" /> 
				<E VAR="gamma" DOMAIN="31"  VALUE="24.3145 * (1 + 0.0107214 * (x - 34.7037))" /> 
				<E VAR="gamma" DOMAIN="32"  VALUE="16.2503 * (1 + 0.014389 * (x - 34.7037))" /> 
				<E VAR="gamma" DOMAIN="33"  VALUE="1.05074 * (1 + 0.0214322 * (x - 36.1825))" /> 
				<E VAR="gamma" DOMAIN="34"  VALUE="0.31534 * (1 + 0.00966829 * (x - 36.1825))" /> 
				<E VAR="gamma" DOMAIN="35"  VALUE="4.90143 * (1 + 0 * (x - 38.4501))" /> 
				<E VAR="gamma" DOMAIN="36"  VALUE="0.305304 * (1 + 0 * (x - 38.4501))" /> 
				<E VAR="gamma" DOMAIN="37"  VALUE="4.90143 * (1 + 0 * (x - 40.7176))" /> 
				<E VAR="gamma" DOMAIN="38"  VALUE="0.311921 * (1 + 0.00540949 * (x - 40.7176))" /> 
				<E VAR="gamma" DOMAIN="39"  VALUE="5.70451 * (1 + 0.0768443 * (x - 52.7456))" /> 
				<E VAR="gamma" DOMAIN="40"  VALUE="0.341555 * (1 + 0.0209529 * (x - 52.7456))" /> 
				<E VAR="gamma" DOMAIN="41"  VALUE="1.06991 * (1 + 0.0243137 * (x - 55.0132))" /> 
				<E VAR="gamma" DOMAIN="42"  VALUE="1.06991 * (1 + 0.0243137 * (x - 55.0132))" /> 
				<E VAR="gamma" DOMAIN="43"  VALUE="3.6464 * (1 + 0.00426689 * (x - 61.7173))" /> 
				<E VAR="gamma" DOMAIN="44"  VALUE="17.7762 * (1 + 0 * (x - 61.7173))" /> 
				<E VAR="gamma" DOMAIN="45"  VALUE="11.9887 * (1 + 0.0074952 * (x - 78.0832))" /> 
				<E VAR="gamma" DOMAIN="46"  VALUE="17.7762 * (1 + 0.00768161 * (x - 78.0832))" /> 
				<E VAR="gamma" DOMAIN="47"  VALUE="25.8909 * (1 + 0.00374053 * (x - 128.265))" /> 
				<E VAR="gamma" DOMAIN="48"  VALUE="33.1692 * (1 + 0.0039904 * (x - 128.265))" /> 
				<E VAR="gamma" DOMAIN="49"  VALUE="3.6464 * (1 + 0.00426689 * (x - 61.7173))" /> 
				<E VAR="gamma" DOMAIN="50"  VALUE="17.7762 * (1 + 0 * (x - 61.7173))" /> 
				<E VAR="gamma" DOMAIN="51"  VALUE="11.9887 * (1 + 0.0074952 * (x - 78.0832))" /> 
				<E VAR="gamma" DOMAIN="52"  VALUE="17.7762 * (1 + 0.00768161 * (x - 78.0832))" /> 
				<E VAR="gamma" DOMAIN="53"  VALUE="25.8909 * (1 + 0.00374053 * (x - 128.265))" /> 
				<E VAR="gamma" DOMAIN="54"  VALUE="33.1692 * (1 + 0.0039904 * (x - 128.265))" /> 
		</FUNCTION> 

		<FUNCTION NAME="StrainStiffening"> 
				<E VAR="alpha" DOMAIN="0"  VALUE="0.606984 * (1 + 0.000105214 * (x - 0))" /> 
				<E VAR="alpha" DOMAIN="1"  VALUE="0.626231 * (1 + 0.00402733 * (x - 5.71822))" /> 
				<E VAR="alpha" DOMAIN="2"  VALUE="0.657385 * (1 + 0.00767345 * (x - 5.71822))" /> 
				<E VAR="alpha" DOMAIN="3"  VALUE="0.779992 * (1 + 0.0234604 * (x - 9.56322))" /> 
				<E VAR="alpha" DOMAIN="4"  VALUE="0.79253 * (1 + 0.0241731 * (x - 9.56322))" /> 
				<E VAR="alpha" DOMAIN="5"  VALUE="1.37423 * (1 + 0.0101408 * (x - 13.4082))" /> 
				<E VAR="alpha" DOMAIN="6"  VALUE="0.897549 * (1 + 0.005106 * (x - 13.4082))" /> 
				<E VAR="alpha" DOMAIN="7"  VALUE="1.37423 * (1 + 0.0041479 * (x - 61.2243))" /> 
				<E VAR="alpha" DOMAIN="8"  VALUE="1.37423 * (1 + 0.00705198 * (x - 61.2243))" /> 
				<E VAR="alpha" DOMAIN="9"  VALUE="2.04462 * (1 + 0.0125487 * (x - 68.8158))" /> 
				<E VAR="alpha" DOMAIN="10"  VALUE="1.51294 * (1 + 0.00449399 * (x - 68.8158))" /> 
				<E VAR="alpha" DOMAIN="11"  VALUE="1.06625 * (1 + 0.00737822 * (x - 20.2109))" /> 
				<E VAR="alpha" DOMAIN="12"  VALUE="1.79766 * (1 + 0.0176918 * (x - 20.2109))" /> 
				<E VAR="alpha" DOMAIN="13"  VALUE="0.648616 * (1 + 0.00147116 * (x - 7.98578))" /> 
				<E VAR="alpha" DOMAIN="14"  VALUE="0.830997 * (1 + 0.0180854 * (x - 7.98578))" /> 
				<E VAR="alpha" DOMAIN="15"  VALUE="1.25141 * (1 + 0.00739927 * (x - 23.7602))" /> 
				<E VAR="alpha" DOMAIN="16"  VALUE="2.19392 * (1 + 0.016467 * (x - 23.7602))" /> 
				<E VAR="alpha" DOMAIN="17"  VALUE="0.658945 * (1 + 0.00231678 * (x - 12.4223))" /> 
				<E VAR="alpha" DOMAIN="18"  VALUE="0.79253 * (1 + 0.0264588 * (x - 12.4223))" /> 
				<E VAR="alpha" DOMAIN="19"  VALUE="1.37423 * (1 + 0.0102005 * (x - 16.2673))" /> 
				<E VAR="alpha" DOMAIN="20"  VALUE="0.897549 * (1 + 0.005106 * (x - 16.2673))" /> 
				<E VAR="alpha" DOMAIN="21"  VALUE="1.42542 * (1 + 0.00526231 * (x - 64.0835))" /> 
				<E VAR="alpha" DOMAIN="22"  VALUE="1.25141 * (1 + 0 * (x - 64.0835))" /> 
				<E VAR="alpha" DOMAIN="23"  VALUE="2.30401 * (1 + 0 * (x - 71.6749))" /> 
				<E VAR="alpha" DOMAIN="24"  VALUE="1.28897 * (1 + 0.00319454 * (x - 71.6749))" /> 
				<E VAR="alpha" DOMAIN="25"  VALUE="0.753836 * (1 + 0.0111343 * (x - 18.3377))" /> 
				<E VAR="alpha" DOMAIN="26"  VALUE="0.693317 * (1 + 0.00618282 * (x - 18.3377))" /> 
				<E VAR="alpha" DOMAIN="27"  VALUE="0.762001 * (1 + 0 * (x - 30.1685))" /> 
				<E VAR="alpha" DOMAIN="28"  VALUE="0.913027 * (1 + 0.0248592 * (x - 30.1685))" /> 
				<E VAR="alpha" DOMAIN="29"  VALUE="1.12161 * (1 + 0.0146137 * (x - 32.4361))" /> 
				<E VAR="alpha" DOMAIN="30"  VALUE="1.09801 * (1 + 0.0147796 * (x - 32.4361))" /> 
				<E VAR="alpha" DOMAIN="31"  VALUE="1.51294 * (1 + 0.00515401 * (x - 34.7037))" /> 
				<E VAR="alpha" DOMAIN="32"  VALUE="1.27063 * (1 + 0.00612552 * (x - 34.7037))" /> 
				<E VAR="alpha" DOMAIN="33"  VALUE="0.907905 * (1 + 0.00721305 * (x - 36.1825))" /> 
				<E VAR="alpha" DOMAIN="34"  VALUE="0.779992 * (1 + 0.00274504 * (x - 36.1825))" /> 
				<E VAR="alpha" DOMAIN="35"  VALUE="1.12161 * (1 + 0 * (x - 38.4501))" /> 
				<E VAR="alpha" DOMAIN="36"  VALUE="0.772967 * (1 + 0 * (x - 38.4501))" /> 
				<E VAR="alpha" DOMAIN="37"  VALUE="1.12161 * (1 + 0 * (x - 40.7176))" /> 
				<E VAR="alpha" DOMAIN="38"  VALUE="0.777611 * (1 + 0.00156509 * (x - 40.7176))" /> 
				<E VAR="alpha" DOMAIN="39"  VALUE="1.18747 * (1 + 0.0379014 * (x - 52.7456))" /> 
				<E VAR="alpha" DOMAIN="40"  VALUE="0.797862 * (1 + 0.00613761 * (x - 52.7456))" /> 
				<E VAR="alpha" DOMAIN="41"  VALUE="0.913086 * (1 + 0.00829859 * (x - 55.0132))" /> 
				<E VAR="alpha" DOMAIN="42"  VALUE="0.913086 * (1 + 0.00829859 * (x - 55.0132))" /> 
				<E VAR="alpha" DOMAIN="43"  VALUE="1.01041 * (1 + 0.00149614 * (x - 61.7173))" /> 
				<E VAR="alpha" DOMAIN="44"  VALUE="1.31842 * (1 + 0 * (x - 61.7173))" /> 
				<E VAR="alpha" DOMAIN="45"  VALUE="1.12949 * (1 + 0.00340866 * (x - 78.0832))" /> 
				<E VAR="alpha" DOMAIN="46"  VALUE="1.31842 * (1 + 0.00337643 * (x - 78.0832))" /> 
				<E VAR="alpha" DOMAIN="47"  VALUE="1.558 * (1 + 0.00187792 * (x - 128.265))" /> 
				<E VAR="alpha" DOMAIN="48"  VALUE="1.75998 * (1 + 0.00218745 * (x - 128.265))" /> 
				<E VAR="alpha" DOMAIN="49"  VALUE="1.01041 * (1 + 0.00149614 * (x - 61.7173))" /> 
				<E VAR="alpha" DOMAIN="50"  VALUE="1.31842 * (1 + 0 * (x - 61.7173))" /> 
				<E VAR="alpha" DOMAIN="51"  VALUE="1.12949 * (1 + 0.00340866 * (x - 78.0832))" /> 
				<E VAR="alpha" DOMAIN="52"  VALUE="1.31842 * (1 + 0.00337643 * (x - 78.0832))" /> 
				<E VAR="alpha" DOMAIN="53"  VALUE="1.558 * (1 + 0.00187792 * (x - 128.265))" /> 
				<E VAR="alpha" DOMAIN="54"  VALUE="1.75998 * (1 + 0.00218745 * (x - 128.265))" /> 
		</FUNCTION> 

</CONDITIONS> 

</NEKTAR>